xyz_mediavendors/__init__.py
xyz_mediavendors/acfun.py
xyz_mediavendors/bilibili.py
xyz_mediavendors/douban.py
xyz_mediavendors/douyin.py
xyz_mediavendors/ecorner.py
xyz_mediavendors/fandengdushu.py
xyz_mediavendors/kaiyan.py
xyz_mediavendors/kuaishou.py
xyz_mediavendors/kugou.py
xyz_mediavendors/kuwo.py
xyz_mediavendors/lanrentingshu.py
xyz_mediavendors/lizhifm.py
xyz_mediavendors/maoerfm.py
xyz_mediavendors/mgtv.py
xyz_mediavendors/miaopai.py
xyz_mediavendors/migu.py
xyz_mediavendors/nangua.py
xyz_mediavendors/netease.py
xyz_mediavendors/pipixia.py
xyz_mediavendors/qq.py
xyz_mediavendors/qutoutiao.py
xyz_mediavendors/simplecast.py
xyz_mediavendors/sohu.py
xyz_mediavendors/ted.py
xyz_mediavendors/tieba.py
xyz_mediavendors/vuevlog.py
xyz_mediavendors/weibo.py
xyz_mediavendors/xiami.py
xyz_mediavendors/xiaoeknow.py
xyz_mediavendors/xiaohongshu.py
xyz_mediavendors/ximalaya.py
xyz_mediavendors/youku.py
xyz_mediavendors/youtube.py
xyz_mediavendors-0.0.1.dist-info/METADATA
xyz_mediavendors-0.0.1.dist-info/WHEEL
xyz_mediavendors-0.0.1.dist-info/top_level.txt
xyz_mediavendors-0.0.1.dist-info/RECORD
